ppllm/__init__.py
ppllm/__main__.py
ppllm/ppl.py
ppllm/utils.py
ppllm-0.2.3.dist-info/licenses/LICENSE
ppllm-0.2.3.dist-info/METADATA
ppllm-0.2.3.dist-info/WHEEL
ppllm-0.2.3.dist-info/top_level.txt
ppllm-0.2.3.dist-info/RECORD
