Metadata-Version: 2.4
Name: ppllm
Version: 0.2.3
Summary: A Python Library to Compute LLM's Perplexity and Surprisal
Author: Paul Lerner
License-Expression: MIT
Project-URL: Homepage, https://github.com/PaulLerner/ppllm
Requires-Python: >=3.10
License-File: LICENSE
Requires-Dist: accelerate>=1.12.0
Requires-Dist: datasets>=3.6.0
Requires-Dist: ipython>=8.37.0
Requires-Dist: jsonargparse>=4.41.0
Requires-Dist: seaborn>=0.13.2
Requires-Dist: vllm>=0.9.1
Dynamic: license-file
